relpath/__init__.py
relpath/test.py
relpath-3.0.5.dist-info/METADATA
relpath-3.0.5.dist-info/WHEEL
relpath-3.0.5.dist-info/top_level.txt
relpath-3.0.5.dist-info/RECORD
