Metadata-Version: 2.1
Name: relpath
Version: 3.0.5
Summary: relative path from the python file itself
Home-page: https://github.co.jp/
Author: le lattelle
Author-email: g.tiger.ml@gmail.com
License: CC0 v1.0
Platform: UNKNOWN
Classifier: Programming Language :: Python :: 3
Classifier: Topic :: Software Development :: Libraries
Classifier: License :: CC0 1.0 Universal (CC0 1.0) Public Domain Dedication
